jodotnetmodules/__init__.py
jodotnetmodules/youtuberequests.py
jodotnetmodules-0.0.2.dist-info/METADATA
jodotnetmodules-0.0.2.dist-info/WHEEL
jodotnetmodules-0.0.2.dist-info/licenses/LICENSE
jodotnetmodules-0.0.2.dist-info/RECORD
