Metadata-Version: 2.1
Name: jodotnetmodules
Version: 0.0.2
Summary: Useful features that you can use with a Discord Bot
Project-URL: Homepage, https://github.com/JoDotNet/JoDotNetModules
Project-URL: Bug Tracker, https://github.com/JoDotNet/JoDotNetModules/issues
Author: JoDotNet
License-File: LICENSE
Classifier: License :: OSI Approved :: MIT License
Classifier: Operating System :: OS Independent
Classifier: Programming Language :: Python :: 3
Requires-Python: >=3.8.0
